{
    "Document date": "Oct-14, 2019",
    "Document summary": "This document is a Letter of Intent for a proposed solar energy project between HALEAKALA RANCH COMPANY and Clearway Renew LLC. The agreement outlines the negotiation and development of a 40 megawatt solar renewable energy project in response to Maui Electric Company, Limited's RFP. The document specifies key conditions such as lease agreements, entitlements, termination clauses, and confidentiality agreements.",
    "Suggested title": "10-14-2019 Solar Energy Project Agreement",
    "Suggested title v2": "Agreement for Solar Project Development",
    "Suggested title v3": "Solar Project Letter of Intent",
    "PPA value": "",
    "Document folder path": "MegaSolar/Unclassified",
    "number_of_pages": 9,
    "original_title": "HR_Clearway_LOI_Fully Executed"
}